pantalaimon/__init__.py
pantalaimon/client.py
pantalaimon/config.py
pantalaimon/daemon.py
pantalaimon/index.py
pantalaimon/log.py
pantalaimon/main.py
pantalaimon/panctl.py
pantalaimon/store.py
pantalaimon/thread_messages.py
pantalaimon/ui.py
pantalaimon-0.10.5.dist-info/LICENSE
pantalaimon-0.10.5.dist-info/METADATA
pantalaimon-0.10.5.dist-info/WHEEL
pantalaimon-0.10.5.dist-info/entry_points.txt
pantalaimon-0.10.5.dist-info/top_level.txt
pantalaimon-0.10.5.dist-info/RECORD
