Metadata-Version: 2.1
Name: pantalaimon
Version: 0.10.5
Summary: A Matrix proxy daemon that adds E2E encryption capabilities.
Home-page: https://github.com/matrix-org/pantalaimon
Author: The Matrix.org Team
Author-email: poljar@termina.org.uk
License: Apache License, Version 2.0
License-File: LICENSE
Requires-Dist: attrs (>=19.3.0)
Requires-Dist: aiohttp (<4.0,>=3.6)
Requires-Dist: appdirs (>=1.4.4)
Requires-Dist: click (>=7.1.2)
Requires-Dist: keyring (>=21.2.1)
Requires-Dist: logbook (>=1.5.3)
Requires-Dist: peewee (>=3.13.1)
Requires-Dist: janus (>=0.5)
Requires-Dist: cachetools (>=3.0.0)
Requires-Dist: prompt-toolkit (<4,>2)
Requires-Dist: matrix-nio[e2e] (<0.21,>=0.20)
Requires-Dist: typing ; python_version < "3.5"
Provides-Extra: ui
Requires-Dist: dbus-python (<1.3,>=1.2) ; extra == 'ui'
Requires-Dist: PyGObject (<3.39,>=3.36) ; extra == 'ui'
Requires-Dist: pydbus (<0.7,>=0.6) ; extra == 'ui'
Requires-Dist: notify2 (<0.4,>=0.3) ; extra == 'ui'
